py_blackboard/__init__.py
py_blackboard/client.py
py_blackboard-0.0.6.dist-info/LICENSE
py_blackboard-0.0.6.dist-info/METADATA
py_blackboard-0.0.6.dist-info/WHEEL
py_blackboard-0.0.6.dist-info/top_level.txt
py_blackboard-0.0.6.dist-info/RECORD
