Metadata-Version: 2.1
Name: py-blackboard
Version: 0.0.6
Summary: Python library to interact with the Blackboard Collaborate APIs.
Home-page: https://github.com/PaoloRollo/py-blackboard
Author: Paolo Rollo
Author-email: paolo.rollo1997@gmail.com
License: UNKNOWN
Platform: UNKNOWN
Classifier: Programming Language :: Python :: 3
Classifier: License :: OSI Approved :: MIT License
Classifier: Operating System :: OS Independent
Requires-Python: >=3.6
